{"type":"provinceCollection", "provinces":[
{"C":"DOM","D":"1974","N":"Azua","X":"-70.833815","Y":"18.580418","Z":"9"},
{"C":"DOM","D":"1969","N":"Bahoruco","X":"-71.330339","Y":"18.514024","Z":"10"},
{"C":"DOM","D":"1970","N":"Barahona","X":"-71.209974","Y":"18.170811","Z":"9"},
{"C":"DOM","D":"1966","N":"Dajabón","X":"-71.601532","Y":"19.43811","Z":"9"},
{"C":"DOM","D":"1985","N":"Distrito Nacional","X":"-69.945812","Y":"18.482868","Z":"11"},
{"C":"DOM","D":"1979","N":"Duarte","X":"-70.087758","Y":"19.243449","Z":"9"},
{"C":"DOM","D":"1986","N":"El Seybo","X":"-69.05559","Y":"18.819387","Z":"9"},
{"C":"DOM","D":"1967","N":"Espaillat","X":"-70.394344","Y":"19.537606","Z":"9"},
{"C":"DOM","D":"1980","N":"Hato Mayor","X":"-69.386138","Y":"18.873725","Z":"9"},
{"C":"DOM","D":"1968","N":"Hermanas","X":"-70.366517","Y":"19.408974","Z":"10"},
{"C":"DOM","D":"1971","N":"Independencia","X":"-71.628919","Y":"18.423849","Z":"9"},
{"C":"DOM","D":"1987","N":"La Altagracia","X":"-68.660842","Y":"18.567187","Z":"9"},
{"C":"DOM","D":"1972","N":"La Estrelleta","X":"-71.599844","Y":"19.004887","Z":"9"},
{"C":"DOM","D":"1988","N":"La Romana","X":"-68.977837","Y":"18.509279","Z":"10"},
{"C":"DOM","D":"1975","N":"La Vega","X":"-70.631633","Y":"19.052067","Z":"9"},
{"C":"DOM","D":"1982","N":"María Trinidad Sánchez","X":"-69.984034","Y":"19.444188","Z":"9"},
{"C":"DOM","D":"1976","N":"Monseñor Nouel","X":"-70.418377","Y":"18.892624","Z":"9"},
{"C":"DOM","D":"1964","N":"Monte Cristi","X":"-71.443936","Y":"19.722095","Z":"9"},
{"C":"DOM","D":"1981","N":"Monte Plata","X":"-69.805063","Y":"18.832574","Z":"9"},
{"C":"DOM","D":"1973","N":"Pedernales","X":"-71.532735","Y":"17.961321","Z":"9"},
{"C":"DOM","D":"1977","N":"Peravia","X":"-70.372743","Y":"18.333489","Z":"10"},
{"C":"DOM","D":"1965","N":"Puerto Plata","X":"-70.801333","Y":"19.744351","Z":"9"},
{"C":"DOM","D":"1983","N":"Samaná","X":"-69.499817","Y":"19.232994","Z":"9"},
{"C":"DOM","D":"1984","N":"San Cristóbal","X":"-70.210066","Y":"18.521477","Z":"9"},
{"C":"DOM","D":"1978","N":"San José de Ocoa","X":"-70.497926","Y":"18.610716","Z":"10"},
{"C":"DOM","D":"1393","N":"San Juan","X":"-71.286271","Y":"18.87967","Z":"9"},
{"C":"DOM","D":"1396","N":"San Pedro de Macorís","X":"-69.369091","Y":"18.547296","Z":"9"},
{"C":"DOM","D":"1395","N":"Sánchez Ramírez","X":"-70.144822","Y":"19.017602","Z":"10"},
{"C":"DOM","D":"1390","N":"Santiago","X":"-70.902866","Y":"19.324201","Z":"9"},
{"C":"DOM","D":"1391","N":"Santiago Rodríguez","X":"-71.310012","Y":"19.383088","Z":"9"},
{"C":"DOM","D":"1394","N":"Santo Domingo","X":"-69.860758","Y":"18.565322","Z":"10"},
{"C":"DOM","D":"1392","N":"Valverde","X":"-71.034593","Y":"19.581727","Z":"10"}
]}