{"type":"provinceCollection", "provinces":[
{"C":"GTM","D":"1948","N":"Alta Verapaz","X":"-90.144333","Y":"15.638542","Z":"8"},
{"C":"GTM","D":"1942","N":"Baja Verapaz","X":"-90.418136","Y":"15.105271","Z":"9"},
{"C":"GTM","D":"1949","N":"Chimaltenango","X":"-90.932629","Y":"14.703265","Z":"9"},
{"C":"GTM","D":"1960","N":"Chiquimula","X":"-89.427118","Y":"14.698037","Z":"9"},
{"C":"GTM","D":"1956","N":"El Progreso","X":"-90.070196","Y":"14.918823","Z":"9"},
{"C":"GTM","D":"1950","N":"Escuintla","X":"-90.992053","Y":"14.166694","Z":"9"},
{"C":"GTM","D":"1951","N":"Guatemala","X":"-90.492644","Y":"14.637236","Z":"9"},
{"C":"GTM","D":"1943","N":"Huehuetenango","X":"-91.559898","Y":"15.661747","Z":"8"},
{"C":"GTM","D":"1959","N":"Izabal","X":"-89.038172","Y":"15.552314","Z":"8"},
{"C":"GTM","D":"1961","N":"Jalapa","X":"-89.948711","Y":"14.632776","Z":"9"},
{"C":"GTM","D":"1962","N":"Jutiapa","X":"-89.888858","Y":"14.222794","Z":"8"},
{"C":"GTM","D":"1944","N":"Petén","X":"-90.014047","Y":"16.970635","Z":"7"},
{"C":"GTM","D":"1945","N":"Quezaltenango","X":"-91.72739","Y":"14.804022","Z":"8"},
{"C":"GTM","D":"3467","N":"Quiché","X":"-90.948171","Y":"15.455801","Z":"8"},
{"C":"GTM","D":"1946","N":"Retalhuleu","X":"-91.782304","Y":"14.435639","Z":"9"},
{"C":"GTM","D":"1953","N":"Sacatepéquez","X":"-90.743425","Y":"14.578174","Z":"10"},
{"C":"GTM","D":"1947","N":"San Marcos","X":"-91.953105","Y":"15.013588","Z":"9"},
{"C":"GTM","D":"1957","N":"Santa Rosa","X":"-90.330538","Y":"14.166087","Z":"9"},
{"C":"GTM","D":"1954","N":"Sololá","X":"-91.25508","Y":"14.726641","Z":"9"},
{"C":"GTM","D":"1952","N":"Suchitepéquez","X":"-91.410531","Y":"14.415502","Z":"9"},
{"C":"GTM","D":"1955","N":"Totonicapán","X":"-91.390551","Y":"15.034968","Z":"9"},
{"C":"GTM","D":"1963","N":"Zacapa","X":"-89.496711","Y":"15.051386","Z":"9"}
]}