{"type":"provinceCollection", "provinces":[
{"C":"TWN","D":"1169","N":"Changhua","X":"120.481938","Y":"23.959365","Z":"9"},
{"C":"TWN","D":"1170","N":"Chiayi","X":"120.523447","Y":"23.453535","Z":"9"},
{"C":"TWN","D":"1171","N":"Chiayi City","X":"120.441861","Y":"23.482917","Z":"12"},
{"C":"TWN","D":"1162","N":"Hsinchu","X":"121.160846","Y":"24.687338","Z":"9"},
{"C":"TWN","D":"1161","N":"Hsinchu City","X":"120.952694","Y":"24.782584","Z":"11"},
{"C":"TWN","D":"1172","N":"Hualien","X":"121.376852","Y":"23.754535","Z":"8"},
{"C":"TWN","D":"1156","N":"Kaohsiung City","X":"120.617319","Y":"22.998764","Z":"8"},
{"C":"TWN","D":"1164","N":"Keelung City","X":"121.707872","Y":"25.112685","Z":"11"},
{"C":"TWN","D":"3415","N":"Kinmen","X":"118.375705","Y":"24.458069","Z":"11"},
{"C":"TWN","D":"1165","N":"Miaoli","X":"120.916765","Y":"24.488708","Z":"9"},
{"C":"TWN","D":"20001","N":"NA","X":"120.068122","Y":"23.488736","Z":"11"},
{"C":"TWN","D":"1173","N":"Nantou","X":"120.986466","Y":"23.848504","Z":"8"},
{"C":"TWN","D":"1167","N":"New Taipei City","X":"121.590007","Y":"24.986095","Z":"9"},
{"C":"TWN","D":"3414","N":"Penghu","X":"119.573735","Y":"23.586565","Z":"10"},
{"C":"TWN","D":"1158","N":"Pingtung","X":"120.674035","Y":"22.488244","Z":"9"},
{"C":"TWN","D":"1174","N":"Taichung City","X":"120.892885","Y":"24.24481","Z":"9"},
{"C":"TWN","D":"1160","N":"Tainan City","X":"120.333428","Y":"23.15412","Z":"9"},
{"C":"TWN","D":"1166","N":"Taipei City","X":"121.559465","Y":"25.082205","Z":"10"},
{"C":"TWN","D":"1177","N":"Taitung","X":"121.039696","Y":"22.865945","Z":"8"},
{"C":"TWN","D":"1168","N":"Taoyuan","X":"121.263098","Y":"24.897857","Z":"9"},
{"C":"TWN","D":"1163","N":"Yilan","X":"121.635201","Y":"24.577076","Z":"9"},
{"C":"TWN","D":"1176","N":"Yunlin","X":"120.388214","Y":"23.687971","Z":"9"}
]}